adipylib/__init__.py
adipylib/core.py
adipylib/keywords.py
adipylib/summarizer.py
adipylib-0.1.5.dist-info/licenses/LICENSE
adipylib-0.1.5.dist-info/METADATA
adipylib-0.1.5.dist-info/WHEEL
adipylib-0.1.5.dist-info/top_level.txt
adipylib-0.1.5.dist-info/RECORD
