Metadata-Version: 2.4
Name: adipylib
Version: 0.1.5
Summary: A Python Study Toolkit for NLP and more.
Author-email: Aditya Rana <adityarana2610@gmail.com>
Project-URL: Homepage, https://github.com/adityarana2610/adipylib
Project-URL: Bug Tracker, https://github.com/adityarana2610/adipylib/issues
Classifier: Programming Language :: Python :: 3
Classifier: License :: OSI Approved :: MIT License
Classifier: Operating System :: OS Independent
Classifier: Topic :: Text Processing
Classifier: Topic :: Scientific/Engineering
Requires-Python: >=3.8
License-File: LICENSE
Requires-Dist: nltk
Requires-Dist: scikit-learn
Dynamic: license-file
